rank_preserving_calibration/__init__.py
rank_preserving_calibration/_numba_utils.py
rank_preserving_calibration/calibration.py
rank_preserving_calibration/metrics.py
rank_preserving_calibration/nearly.py
rank_preserving_calibration/ovr_isotonic.py
rank_preserving_calibration-0.7.1.dist-info/WHEEL
rank_preserving_calibration-0.7.1.dist-info/METADATA
rank_preserving_calibration-0.7.1.dist-info/RECORD
