Metadata-Version: 2.3
Name: rank_preserving_calibration
Version: 0.7.1
Summary: Rank-preserving calibration of multiclass probabilities via Dykstra's projections and ADMM.
Keywords: calibration,machine learning,multiclass,isotonic,dykstra,admm
Author: Gaurav Sood
Author-email: Gaurav Sood <contact@gsood.com>
Classifier: Development Status :: 4 - Beta
Classifier: Intended Audience :: Science/Research
Classifier: License :: OSI Approved :: MIT License
Classifier: Programming Language :: Python :: 3
Classifier: Programming Language :: Python :: 3.12
Classifier: Programming Language :: Python :: 3.13
Classifier: Programming Language :: Python :: 3.14
Classifier: Topic :: Scientific/Engineering :: Mathematics
Requires-Dist: numpy>=1.20
Requires-Dist: sphinx>=7.0 ; extra == 'docs'
Requires-Dist: furo>=2024.1.29 ; extra == 'docs'
Requires-Dist: sphinx-autodoc-typehints>=1.25 ; extra == 'docs'
Requires-Dist: sphinx-copybutton>=0.5 ; extra == 'docs'
Requires-Dist: myst-nb>=1.0 ; extra == 'docs'
Requires-Dist: jupyter ; extra == 'docs'
Requires-Dist: ipykernel>=6.0 ; extra == 'docs'
Requires-Dist: scikit-learn>=1.0 ; extra == 'docs'
Requires-Dist: matplotlib>=3.0 ; extra == 'docs'
Requires-Dist: seaborn>=0.11 ; extra == 'docs'
Requires-Dist: plotly>=5.0 ; extra == 'docs'
Requires-Dist: numba>=0.56 ; extra == 'performance'
Requires-Python: >=3.12
Project-URL: Documentation, https://finite_sample.github.io/rank_preserving_calibration/
Project-URL: Homepage, https://github.com/finite_sample/rank_preserving_calibration
Project-URL: Issues, https://github.com/finite_sample/rank_preserving_calibration/issues
Project-URL: Source, https://github.com/finite_sample/rank_preserving_calibration
Provides-Extra: docs
Provides-Extra: performance
